linguanova
